ginee_x/agent/__init__.py
ginee_x/chat/__init__.py
ginee_x/knowledge/__init__.py
ginee_x-0.1.dist-info/METADATA
ginee_x-0.1.dist-info/WHEEL
ginee_x-0.1.dist-info/top_level.txt
ginee_x-0.1.dist-info/RECORD
